tinycreeper/__version__.py
tinycreeper/cli.py
tinycreeper/cli_utils.py
tinycreeper-0.0.7.dist-info/LICENSE
tinycreeper-0.0.7.dist-info/METADATA
tinycreeper-0.0.7.dist-info/WHEEL
tinycreeper-0.0.7.dist-info/entry_points.txt
tinycreeper-0.0.7.dist-info/top_level.txt
tinycreeper-0.0.7.dist-info/RECORD
